myliu_ragflow_mcp_server_continue/__init__.py
myliu_ragflow_mcp_server_continue/config.py
myliu_ragflow_mcp_server_continue/server.py
myliu_ragflow_mcp_server_continue-0.1.0.dist-info/WHEEL
myliu_ragflow_mcp_server_continue-0.1.0.dist-info/entry_points.txt
myliu_ragflow_mcp_server_continue-0.1.0.dist-info/METADATA
myliu_ragflow_mcp_server_continue-0.1.0.dist-info/RECORD
