Metadata-Version: 2.3
Name: myliu-ragflow-mcp-server-continue
Version: 0.1.0
Summary: RAGFlow MCP Server Continue
Author: liumengyao
Author-email: liumengyao <liumengyao@ieisystem.com>
Requires-Dist: mcp>=1.20.0
Requires-Dist: ragflow-sdk>=0.21.1
Requires-Python: >=3.10
